incertidumbres/__init__.py
incertidumbres/incertidumbres.py
incertidumbres/test.py
incertidumbres/test2 copy.py
incertidumbres/test2.py
incertidumbres-0.0.8.dist-info/LICENSE
incertidumbres-0.0.8.dist-info/METADATA
incertidumbres-0.0.8.dist-info/WHEEL
incertidumbres-0.0.8.dist-info/top_level.txt
incertidumbres-0.0.8.dist-info/RECORD
