Metadata-Version: 2.2
Name: incertidumbres
Version: 0.0.8
Summary: Calcula incertidumbre de mediciones de laboratorio
Author-email: Emerson Warhman <edwarhman@gmail.com>
Project-URL: Homepage, https://github.com/pypa/sampleproject
Project-URL: Issues, https://github.com/pypa/sampleproject/issues
Classifier: Programming Language :: Python :: 3
Classifier: License :: OSI Approved :: MIT License
Classifier: Operating System :: OS Independent
Requires-Python: >=3.11
License-File: LICENSE
